libpt-0.4.2.dist-info/METADATA
libpt-0.4.2.dist-info/WHEEL
libpt/__init__.py
libpt/libpt.cpython-311-x86_64-linux-gnu.so
libpt-0.4.2.dist-info/RECORD
