Metadata-Version: 2.1
Name: libpt
Version: 0.4.2
Classifier: Programming Language :: Rust
Classifier: Programming Language :: Python :: Implementation :: CPython
Classifier: Programming Language :: Python :: Implementation :: PyPy
Summary: Personal multitool
Keywords: library
Home-Page: https://git.cscherr.de/PlexSheep/pt
Author: Christoph J. Scherr <software@cscherr.de>
Author-email: Christoph J. Scherr <software@cscherr.de>
License: MIT
Requires-Python: >=3.8
Project-URL: Source Code, https://git.cscherr.de/PlexSheep/pt
